tjc_gym/__init__.py
tjc_gym/envs/__init__.py
tjc_gym/envs/rendering.py
tjc_gym/envs/traffic_junction_continuous_env.py
tjc_gym-0.1.0.dist-info/METADATA
tjc_gym-0.1.0.dist-info/WHEEL
tjc_gym-0.1.0.dist-info/top_level.txt
tjc_gym-0.1.0.dist-info/RECORD
