Metadata-Version: 2.1
Name: tjc-gym
Version: 0.1.0
Summary: OpenAI Gym environment of Traffic Junction with continuous action space
Home-page: https://github.com/jakobdybdahl/tjc-gym
Author: Jakob Dybdahl, Rasmus Thorsen
Author-email: dybdahl@smukand.dk
License: MIT License
Platform: UNKNOWN
Classifier: Programming Language :: Python :: 3.6
Classifier: Programming Language :: Python :: 3.7
Classifier: Programming Language :: Python :: 3.8
Classifier: Programming Language :: Python :: 3.9
Requires-Dist: gym (==0.21.0)
Requires-Dist: numpy (>=1.21.4)
Requires-Dist: pyglet (>=1.5.21)
